tabular_augmentation/__init__.py
tabular_augmentation/custom_smote.py
tabular_augmentation/cvae.py
tabular_augmentation/mixup.py
tabular_augmentation/sdv_synthesizer.py
tabular_augmentation/smote.py
tabular_augmentation/utils.py
tabular_augmentation/tab_ddpm/__init__.py
tabular_augmentation/tab_ddpm/gaussian_multinomial_diffsuion.py
tabular_augmentation/tab_ddpm/modules.py
tabular_augmentation/tab_ddpm/synthesis.py
tabular_augmentation/tab_ddpm/utils.py
tabular_augmentation/tab_ddpm/lib/__init__.py
tabular_augmentation/tab_ddpm/lib/data.py
tabular_augmentation/tab_ddpm/lib/deep.py
tabular_augmentation/tab_ddpm/lib/env.py
tabular_augmentation/tab_ddpm/lib/metrics.py
tabular_augmentation/tab_ddpm/lib/util.py
tabular_augmentation/tab_ddpm/scripts/__init__.py
tabular_augmentation/tab_ddpm/scripts/eval_catboost.py
tabular_augmentation/tab_ddpm/scripts/eval_mlp.py
tabular_augmentation/tab_ddpm/scripts/eval_seeds.py
tabular_augmentation/tab_ddpm/scripts/eval_seeds_simple.py
tabular_augmentation/tab_ddpm/scripts/eval_simple.py
tabular_augmentation/tab_ddpm/scripts/pipeline.py
tabular_augmentation/tab_ddpm/scripts/resample_privacy.py
tabular_augmentation/tab_ddpm/scripts/sample.py
tabular_augmentation/tab_ddpm/scripts/train.py
tabular_augmentation/tab_ddpm/scripts/tune_ddpm.py
tabular_augmentation/tab_ddpm/scripts/tune_evaluation_model.py
tabular_augmentation/tab_ddpm/scripts/utils_train.py
tabular_augmentation-0.0.18.dist-info/LICENSE
tabular_augmentation-0.0.18.dist-info/METADATA
tabular_augmentation-0.0.18.dist-info/WHEEL
tabular_augmentation-0.0.18.dist-info/top_level.txt
tabular_augmentation-0.0.18.dist-info/RECORD
