Metadata-Version: 2.1
Name: tabular-augmentation
Version: 0.0.18
Summary: Implementing easy-to-use methods for classical and novel tabular data augmentation and synthesis.
Author-email: zhuxiaofei <dylan@zhxfei.com>
Project-URL: Homepage, https://github.com/zhxfei/tabular_augmentation
Project-URL: Bug Tracker, https://github.com/zhxfei/tabular_augmentation/issues
Classifier: Programming Language :: Python :: 3
Classifier: License :: OSI Approved :: MIT License
Classifier: Operating System :: OS Independent
Requires-Python: >=3.9
License-File: LICENSE
Requires-Dist: ctgan >=0.7.4
Requires-Dist: torchvision
Requires-Dist: sdv >=1.3.0
Requires-Dist: tensorboard >=2.13.0
Requires-Dist: imbalanced-learn >=0.11.0
Requires-Dist: scikit-learn >=1.0.2
Requires-Dist: ema-pytorch
Requires-Dist: xgboost ==1.7.6
Requires-Dist: category-encoders
Requires-Dist: icecream
Requires-Dist: catboost
Requires-Dist: libzero ==0.0.8
Requires-Dist: tomli ==1.2.2
Requires-Dist: tomli-w ==0.4.0
Requires-Dist: optuna ==2.10.1
Requires-Dist: tqdm
Requires-Dist: rtdl
